{
  "multipart": [
    {
      "apply": {
        "model": "minekea:block/containers/crates/crimson",
        "x": 90,
        "y": 90
      },
      "when": {
        "axis": "x"
      }
    },
    {
      "apply": {
        "model": "minekea:block/containers/crates/crimson"
      },
      "when": {
        "axis": "y"
      }
    },
    {
      "apply": {
        "model": "minekea:block/containers/crates/crimson",
        "x": 90
      },
      "when": {
        "axis": "z"
      }
    }
  ]
}